mehrp/__init__.py
mehrp/__main__.py
mehrp/mehrp.py
mehrp/mehrp.wav
mehrp-0.0.1.dist-info/LICENSE
mehrp-0.0.1.dist-info/METADATA
mehrp-0.0.1.dist-info/WHEEL
mehrp-0.0.1.dist-info/entry_points.txt
mehrp-0.0.1.dist-info/top_level.txt
mehrp-0.0.1.dist-info/RECORD
