Metadata-Version: 2.1
Name: mehrp
Version: 0.0.1
Summary: Easy beeping (merhp) from the terminal.
Home-page: https://github.com/c0yote/mehrp
Author: U.G. Wilson
Author-email: ugwilson@gmail.com
License: UNKNOWN
Keywords: beep notification
Platform: UNKNOWN
Classifier: Development Status :: 5 - Production/Stable
Classifier: Environment :: Console
Classifier: Intended Audience :: Developers
Classifier: Intended Audience :: System Administrators 
Classifier: Topic :: Software Development :: Build Tools
Classifier: License :: OSI Approved :: MIT License
Classifier: Topic :: System :: Monitoring
Classifier: Topic :: Terminals
Classifier: Topic :: Utilities
Classifier: Programming Language :: Python :: 3.7
Requires-Dist: simpleaudio
